chartify_helpers/ExtraCallouts.py
chartify_helpers/StackedBar.py
chartify_helpers/__init__.py
chartify_helpers-1.2.2.dist-info/LICENSE
chartify_helpers-1.2.2.dist-info/METADATA
chartify_helpers-1.2.2.dist-info/WHEEL
chartify_helpers-1.2.2.dist-info/top_level.txt
chartify_helpers-1.2.2.dist-info/RECORD
