Metadata-Version: 2.1
Name: chartify-helpers
Version: 1.2.2
Summary: Some lightweight helper functions which add readability/functionality to Spotify's chartify library
Home-page: https://github.com/KristofPusztai/chartify-helpers
Author: Kristof Pusztai
Author-email: Kristof Pusztai <kpusztai@berkeley.edu>
License: 
Project-URL: Homepage, https://github.com/KristofPusztai/chartify-helpers
Classifier: Programming Language :: Python :: 3
Classifier: License :: OSI Approved :: Apache Software License
Classifier: Operating System :: OS Independent
Requires-Python: >=3.9
License-File: LICENSE
Requires-Dist: chartify
Requires-Dist: numpy
